pycev/__init__.py
pycev/pycev.py
pycev-0.1.0.dist-info/LICENSE
pycev-0.1.0.dist-info/METADATA
pycev-0.1.0.dist-info/WHEEL
pycev-0.1.0.dist-info/top_level.txt
pycev-0.1.0.dist-info/RECORD
