Metadata-Version: 2.1
Name: pycev
Version: 0.1.0
Summary: Schweitzer Engineering Laboratories (SEL) Compressed EVent (CEV) Reader
Home-page: https://github.com/engineerjoe440/pycev
Author: Joe Stanley
Author-email: joe_stanley@selinc.com
Project-URL: Source Repository, https://github.com/engineerjoe440/pycev
Project-URL: Bug Tracker, https://github.com/engineerjoe440/pycev/issues
Project-URL: Documentation, https://engineerjoe440.github.io/pycev/
Classifier: Programming Language :: Python :: 3
Classifier: License :: OSI Approved :: MIT License
Classifier: Operating System :: OS Independent
License-File: LICENSE
